Workbook
Name Slicer_Quarters__Order_Date: #N/A
Name Slicer_State: #N/A

Sheet Insights
A1: Overall Performance
A3: Total sales amount reached 69K, supported by 678 units sold.
A4: Profit stands at 13K, resulting in a strong Average Order Value (AOV) of 18K.
A5: The overall numbers show stable performance with solid profitability per order.
A7: Geographic Performance
A9: Pune leads all regions with 9K in sales, outperforming other states such as Mathura, Indore, Delhi, and Chandigarh (each around 6K).
A10: The concentration of revenue in a single state indicates a potential geographic dependency that should be monitored.
A12: Customer Insights
A14: Harivansh is the highest-value customer at 5.7K, nearly doubling other key customers such as Sarita, Shiva, Shrichand, and Shruti.
A15: This suggests that a small group of customers contributes disproportionately to total revenue—prime targets for retention strategies.
A17: Category & Payment Behavior
A19: Clothing dominates quantity share at 56%, followed by Electronics (24%) and Furniture (20%).
... A51: “Pay now, express shipping” perks

Sheet Dashboard

Sheet PivotTables
A3: Row Labels | B3: Sum of Amount | D3: Row Labels | E3: Sum of Profit | G3: Row Labels | H3: Sum of Profit | J3: Row Labels | K3: Sum of Quantity
A4: Maharashtra | B4: 12730 | D4: Qtr1 | E4: 12616 | G4: Phones | H4: 2277 | J4: COD | K4: 0.46755162
A5: Madhya Pradesh | B5: 9629 | D5: Grand Total | E5: 12616 | G5: Bookcases | H5: 2209 | J5: Credit Card | K5: 0.14454277
A6: Uttar Pradesh | B6: 7138 | G6: Accessories | H6: 1843 | J6: Debit Card | K6: 0.11061947
A7: Delhi | B7: 5570 | G7: Printers | H7: 1490 | J7: EMI | K7: 0.12094395
A8: Punjab | B8: 5221 | G8: Chairs | H8: 1189 | J8: UPI | K8: 0.15634218
A9: West Bengal | B9: 4253 | G9: Grand Total | H9: 9008 | J9: Grand Total | K9: 1
A10: Grand Total | B10: 44541
J11: Row Labels | K11: Sum of Quantity
J12: Clothing | K12: 379
J13: Electronics | K13: 165
J14: Furniture | K14: 134
J15: Grand Total | K15: 678
J19: Row Labels | K19: Sum of PositiveProfit | L19: Sum of NegativeProfit
J20: Jan | K20: 4502 | L20: 0
J21: Feb | K21: 5271 | L21: 0
D22: Row Labels | E22: Sum of Amount | J22: Mar | K22: 2843 | L22: 0
D23: Chandigarh | E23: 6342 | G23: Row Labels | H23: Sum of Amount | J23: Grand Total | K23: 12616 | L23: 0
D24: Delhi | E24: 5570 | G24: Harivansh | H24: 5729
A25: Sum of AOV | D25: Indore | E25: 6180 | G25: Sarita | H25: 3138
A26: 17836.483 | D26: Mathura | E26: 6127 | G26: Shiva | H26: 2927
D27: Pune | E27: 9287 | G27: Shrichand | H27: 3311
A28: Sum of Amount | D28: Grand Total | E28: 33506 | G28: Shruti | H28: 2204
A29: 68540 | G29: Grand Total | H29: 17309
A31: Sum of Profit
A32: 12616
A34: Sum of Quantity
A35: 678

Sheet database
A1: Order ID | B1: Order Date | C1: CustomerName | D1: State | E1: City | F1: Amount | G1: Profit | H1: Quantity | I1: Category | J1: Sub-Category | K1: Payment Mode | L1: AOV
A2: B-25601 | B2: 43191 | C2: Bharat | D2: Gujarat | E2: Ahmedabad | F2: =_xlfn.XLOOKUP(Orders4[[#This Row],[Order ID]],Details!$A:$A, Details!$B:$B) -> 80 | G2: =_xlfn.XLOOKUP(Orders4[[#This Row],[Order ID]],Details!$A:$A,Details!C:C) -> -56 | H2: =_xlfn.XLOOKUP(Orders4[[#This Row],[Order ID]],Details!$A:$A,Details!$D:$D) -> 4 | I2: =_xlfn.XLOOKUP(Orders4[[#This Row],[Order ID]],Details!A:A,Details!$E:$E) -> Electronics | J2: =_xlfn.XLOOKUP(Orders4[[#This Row],[Order ID]],Details!$A:$A,Details!$F:$F) -> Electronic Games | K2: =_xlfn.XLOOKUP(Orders4[[#This Row],[Order ID]],Details!$A:$A,Details!$G:$G) -> UPI | L2: =Orders4[[#This Row],[Amount]]/Orders4[[#This Row],[Quantity]] -> 20
A3: B-25602 | B3: 43191 | C3: Vrinda | D3: Maharashtra | E3: Pune | F3: =_xlfn.XLOOKUP(Orders4[[#This Row],[Order ID]],Details!$A:$A, Details!$B:$B) -> 2617 | G3: =_xlfn.XLOOKUP(Orders4[[#This Row],[Order ID]],Details!$A:$A,Details!C:C) -> 1151 | H3: =_xlfn.XLOOKUP(Orders4[[#This Row],[Order ID]],Details!$A:$A,Details!$D:$D) -> 4 | I3: =_xlfn.XLOOKUP(Orders4[[#This Row],[Order ID]],Details!A:A,Details!$E:$E) -> Electronics | J3: =_xlfn.XLOOKUP(Orders4[[#This Row],[Order ID]],Details!$A:$A,Details!$F:$F) -> Phones | K3: =_xlfn.XLOOKUP(Orders4[[#This Row],[Order ID]],Details!$A:$A,Details!$G:$G) -> Credit Card | L3: =Orders4[[#This Row],[Amount]]/Orders4[[#This Row],[Quantity]] -> 654.25
A4: B-25603 | B4: 43193 | C4: Jahan | D4: Madhya Pradesh | E4: Bhopal | F4: =_xlfn.XLOOKUP(Orders4[[#This Row],[Order ID]],Details!$A:$A, Details!$B:$B) -> 12 | G4: =_xlfn.XLOOKUP(Orders4[[#This Row],[Order ID]],Details!$A:$A,Details!C:C) -> 1 | H4: =_xlfn.XLOOKUP(Orders4[[#This Row],[Order ID]],Details!$A:$A,Details!$D:$D) -> 2 | I4: =_xlfn.XLOOKUP(Orders4[[#This Row],[Order ID]],Details!A:A,Details!$E:$E) -> Clothing | J4: =_xlfn.XLOOKUP(Orders4[[#This Row],[Order ID]],Details!$A:$A,Details!$F:$F) -> Hankerchief | K4: =_xlfn.XLOOKUP(Orders4[[#This Row],[Order ID]],Details!$A:$A,Details!$G:$G) -> COD | L4: =Orders4[[#This Row],[Amount]]/Orders4[[#This Row],[Quantity]] -> 6
A5: B-25604 | B5: 43193 | C5: Divsha | D5: Rajasthan | E5: Jaipur | F5: =_xlfn.XLOOKUP(Orders4[[#This Row],[Order ID]],Details!$A:$A, Details!$B:$B) -> 65 | G5: =_xlfn.XLOOKUP(Orders4[[#This Row],[Order ID]],Details!$A:$A,Details!C:C) -> 17 | H5: =_xlfn.XLOOKUP(Orders4[[#This Row],[Order ID]],Details!$A:$A,Details!$D:$D) -> 2 | I5: =_xlfn.XLOOKUP(Orders4[[#This Row],[Order ID]],Details!A:A,Details!$E:$E) -> Clothing | J5: =_xlfn.XLOOKUP(Orders4[[#This Row],[Order ID]],Details!$A:$A,Details!$F:$F) -> T-shirt | K5: =_xlfn.XLOOKUP(Orders4[[#This Row],[Order ID]],Details!$A:$A,Details!$G:$G) -> UPI | L5: =Orders4[[#This Row],[Amount]]/Orders4[[#This Row],[Quantity]] -> 32.5
A6: B-25605 | B6: 43195 | C6: Kasheen | D6: West Bengal | E6: Kolkata | F6: =_xlfn.XLOOKUP(Orders4[[#This Row],[Order ID]],Details!$A:$A, Details!$B:$B) -> 75 | G6: =_xlfn.XLOOKUP(Orders4[[#This Row],[Order ID]],Details!$A:$A,Details!C:C) -> 0 | H6: =_xlfn.XLOOKUP(Orders4[[#This Row],[Order ID]],Details!$A:$A,Details!$D:$D) -> 7 | I6: =_xlfn.XLOOKUP(Orders4[[#This Row],[Order ID]],Details!A:A,Details!$E:$E) -> Clothing | J6: =_xlfn.XLOOKUP(Orders4[[#This Row],[Order ID]],Details!$A:$A,Details!$F:$F) -> Saree | K6: =_xlfn.XLOOKUP(Orders4[[#This Row],[Order ID]],Details!$A:$A,Details!$G:$G) -> EMI | L6: =Orders4[[#This Row],[Amount]]/Orders4[[#This Row],[Quantity]] -> 10.714286
A7: B-25606 | B7: 43196 | C7: Hazel | D7: Karnataka | E7: Bangalore | F7: =_xlfn.XLOOKUP(Orders4[[#This Row],[Order ID]],Details!$A:$A, Details!$B:$B) -> 87 | G7: =_xlfn.XLOOKUP(Orders4[[#This Row],[Order ID]],Details!$A:$A,Details!C:C) -> 4 | H7: =_xlfn.XLOOKUP(Orders4[[#This Row],[Order ID]],Details!$A:$A,Details!$D:$D) -> 2 | I7: =_xlfn.XLOOKUP(Orders4[[#This Row],[Order ID]],Details!A:A,Details!$E:$E) -> Clothing | J7: =_xlfn.XLOOKUP(Orders4[[#This Row],[Order ID]],Details!$A:$A,Details!$F:$F) -> Shirt | K7: =_xlfn.XLOOKUP(Orders4[[#This Row],[Order ID]],Details!$A:$A,Details!$G:$G) -> COD | L7: =Orders4[[#This Row],[Amount]]/Orders4[[#This Row],[Quantity]] -> 43.5
A8: B-25607 | B8: 43196 | C8: Sonakshi | D8: Jammu and Kashmir | E8: Kashmir | F8: =_xlfn.XLOOKUP(Orders4[[#This Row],[Order ID]],Details!$A:$A, Details!$B:$B) -> 50 | G8: =_xlfn.XLOOKUP(Orders4[[#This Row],[Order ID]],Details!$A:$A,Details!C:C) -> -15 | H8: =_xlfn.XLOOKUP(Orders4[[#This Row],[Order ID]],Details!$A:$A,Details!$D:$D) -> 4 | I8: =_xlfn.XLOOKUP(Orders4[[#This Row],[Order ID]],Details!A:A,Details!$E:$E) -> Clothing | J8: =_xlfn.XLOOKUP(Orders4[[#This Row],[Order ID]],Details!$A:$A,Details!$F:$F) -> Leggings | K8: =_xlfn.XLOOKUP(Orders4[[#This Row],[Order ID]],Details!$A:$A,Details!$G:$G) -> COD | L8: =Orders4[[#This Row],[Amount]]/Orders4[[#This Row],[Quantity]] -> 12.5
A9: B-25608 | B9: 43198 | C9: Aarushi | D9: Tamil Nadu | E9: Chennai | F9: =_xlfn.XLOOKUP(Orders4[[#This Row],[Order ID]],Details!$A:$A, Details!$B:$B) -> 1364 | G9: =_xlfn.XLOOKUP(Orders4[[#This Row],[Order ID]],Details!$A:$A,Details!C:C) -> 1864 | H9: =_xlfn.XLOOKUP(Orders4[[#This Row],[Order ID]],Details!$A:$A,Details!$D:$D) -> 5 | I9: =_xlfn.XLOOKUP(Orders4[[#This Row],[Order ID]],Details!A:A,Details!$E:$E) -> Furniture | J9: =_xlfn.XLOOKUP(Orders4[[#This Row],[Order ID]],Details!$A:$A,Details!$F:$F) -> Tables | K9: =_xlfn.XLOOKUP(Orders4[[#This Row],[Order ID]],Details!$A:$A,Details!$G:$G) -> Credit Card | L9: =Orders4[[#This Row],[Amount]]/Orders4[[#This Row],[Quantity]] -> 272.8
A10: B-25609 | B10: 43199 | C10: Jitesh | D10: Uttar Pradesh | E10: Lucknow | F10: =_xlfn.XLOOKUP(Orders4[[#This Row],[Order ID]],Details!$A:$A, Details!$B:$B) -> 485 | G10: =_xlfn.XLOOKUP(Orders4[[#This Row],[Order ID]],Details!$A:$A,Details!C:C) -> 29 | H10: =_xlfn.XLOOKUP(Orders4[[#This Row],[Order ID]],Details!$A:$A,Details!$D:$D) -> 4 | I10: =_xlfn.XLOOKUP(Orders4[[#This Row],[Order ID]],Details!A:A,Details!$E:$E) -> Electronics | J10: =_xlfn.XLOOKUP(Orders4[[#This Row],[Order ID]],Details!$A:$A,Details!$F:$F) -> Electronic Games | K10: =_xlfn.XLOOKUP(Orders4[[#This Row],[Order ID]],Details!$A:$A,Details!$G:$G) -> COD | L10: =Orders4[[#This Row],[Amount]]/Orders4[[#This Row],[Quantity]] -> 121.25
A11: B-25610 | B11: 43199 | C11: Yogesh | D11: Bihar | E11: Patna | F11: =_xlfn.XLOOKUP(Orders4[[#This Row],[Order ID]],Details!$A:$A, Details!$B:$B) -> 43 | G11: =_xlfn.XLOOKUP(Orders4[[#This Row],[Order ID]],Details!$A:$A,Details!C:C) -> 0 | H11: =_xlfn.XLOOKUP(Orders4[[#This Row],[Order ID]],Details!$A:$A,Details!$D:$D) -> 3 | I11: =_xlfn.XLOOKUP(Orders4[[#This Row],[Order ID]],Details!A:A,Details!$E:$E) -> Clothing | J11: =_xlfn.XLOOKUP(Orders4[[#This Row],[Order ID]],Details!$A:$A,Details!$F:$F) -> Saree | K11: =_xlfn.XLOOKUP(Orders4[[#This Row],[Order ID]],Details!$A:$A,Details!$G:$G) -> Debit Card | L11: =Orders4[[#This Row],[Amount]]/Orders4[[#This Row],[Quantity]] -> 14.333333
A12: B-25611 | B12: 43201 | C12: Anita | D12: Kerala | E12: Thiruvananthapuram | F12: =_xlfn.XLOOKUP(Orders4[[#This Row],[Order ID]],Details!$A:$A, Details!$B:$B) -> 160 | G12: =_xlfn.XLOOKUP(Orders4[[#This Row],[Order ID]],Details!$A:$A,Details!C:C) -> -59 | H12: =_xlfn.XLOOKUP(Orders4[[#This Row],[Order ID]],Details!$A:$A,Details!$D:$D) -> 2 | I12: =_xlfn.XLOOKUP(Orders4[[#This Row],[Order ID]],Details!A:A,Details!$E:$E) -> Clothing | J12: =_xlfn.XLOOKUP(Orders4[[#This Row],[Order ID]],Details!$A:$A,Details!$F:$F) -> Saree | K12: =_xlfn.XLOOKUP(Orders4[[#This Row],[Order ID]],Details!$A:$A,Details!$G:$G) -> EMI | L12: =Orders4[[#This Row],[Amount]]/Orders4[[#This Row],[Quantity]] -> 80
A13: B-25612 | B13: 43202 | C13: Shrichand | D13: Punjab | E13: Chandigarh | F13: =_xlfn.XLOOKUP(Orders4[[#This Row],[Order ID]],Details!$A:$A, Details!$B:$B) -> 259 | G13: =_xlfn.XLOOKUP(Orders4[[#This Row],[Order ID]],Details!$A:$A,Details!C:C) -> -55 | H13: =_xlfn.XLOOKUP(Orders4[[#This Row],[Order ID]],Details!$A:$A,Details!$D:$D) -> 2 | I13: =_xlfn.XLOOKUP(Orders4[[#This Row],[Order ID]],Details!A:A,Details!$E:$E) -> Furniture | J13: =_xlfn.XLOOKUP(Orders4[[#This Row],[Order ID]],Details!$A:$A,Details!$F:$F) -> Chairs | K13: =_xlfn.XLOOKUP(Orders4[[#This Row],[Order ID]],Details!$A:$A,Details!$G:$G) -> COD | L13: =Orders4[[#This Row],[Amount]]/Orders4[[#This Row],[Quantity]] -> 129.5
... A501: B-26100 | B501: 43190 | C501: Hitika | D501: Madhya Pradesh | E501: Indore | F501: =_xlfn.XLOOKUP(Orders4[[#This Row],[Order ID]],Details!$A:$A, Details!$B:$B) -> 828 | G501: =_xlfn.XLOOKUP(Orders4[[#This Row],[Order ID]],Details!$A:$A,Details!C:C) -> 230 | H501: =_xlfn.XLOOKUP(Orders4[[#This Row],[Order ID]],Details!$A:$A,Details!$D:$D) -> 2 | I501: =_xlfn.XLOOKUP(Orders4[[#This Row],[Order ID]],Details!A:A,Details!$E:$E) -> Furniture | J501: =_xlfn.XLOOKUP(Orders4[[#This Row],[Order ID]],Details!$A:$A,Details!$F:$F) -> Chairs | K501: =_xlfn.XLOOKUP(Orders4[[#This Row],[Order ID]],Details!$A:$A,Details!$G:$G) -> COD | L501: =Orders4[[#This Row],[Amount]]/Orders4[[#This Row],[Quantity]] -> 414
L502: =SUM(L2:L501) -> 50016.903

Sheet Orders
A1: Order ID | B1: Order Date | C1: CustomerName | D1: State | E1: City
A2: B-26055 | B2: 43169 | C2: Harivansh | D2: Uttar Pradesh | E2: Mathura
A3: B-25993 | B3: 43134 | C3: Madhav | D3: Delhi | E3: Delhi
A4: B-25973 | B4: 43124 | C4: Madan Mohan | D4: Uttar Pradesh | E4: Mathura
A5: B-25923 | B5: 43461 | C5: Gopal | D5: Maharashtra | E5: Mumbai
A6: B-25757 | B6: 43333 | C6: Vishakha | D6: Madhya Pradesh | E6: Indore
A7: B-25967 | B7: 43121 | C7: Sudevi | D7: Uttar Pradesh | E7: Prayagraj
A8: B-25955 | B8: 43116 | C8: Shiva | D8: Maharashtra | E8: Pune
A9: B-26093 | B9: 43186 | C9: Sarita | D9: Maharashtra | E9: Pune
A10: B-25798 | B10: 43374 | C10: Shishu | D10: Andhra Pradesh | E10: Hyderabad
A11: B-25602 | B11: 43191 | C11: Vrinda | D11: Maharashtra | E11: Pune
A12: B-25858 | B12: 43417 | C12: Uudhav | D12: Maharashtra | E12: Mumbai
A13: B-25969 | B13: 43121 | C13: Shreyshi | D13: Gujarat | E13: Surat
... A501: B-26095 | B501: 43187 | C501: Monisha | D501: Rajasthan | E501: Jaipur

Sheet Details
A1: Order ID | B1: Amount | C1: Profit | D1: Quantity | E1: Category | F1: Sub-Category | G1: PaymentMode
A2: B-25681 | B2: 1096 | C2: 658 | D2: 7 | E2: Electronics | F2: Electronic Games | G2: COD
A3: B-26055 | B3: 5729 | C3: 64 | D3: 14 | E3: Furniture | F3: Chairs | G3: EMI
A4: B-25955 | B4: 2927 | C4: 146 | D4: 8 | E4: Furniture | F4: Bookcases | G4: EMI
A5: B-26093 | B5: 2847 | C5: 712 | D5: 8 | E5: Electronics | F5: Printers | G5: Credit Card
A6: B-25602 | B6: 2617 | C6: 1151 | D6: 4 | E6: Electronics | F6: Phones | G6: Credit Card
A7: B-25881 | B7: 2244 | C7: 247 | D7: 4 | E7: Clothing | F7: Trousers | G7: Credit Card
A8: B-25696 | B8: 275 | C8: -275 | D8: 4 | E8: Clothing | F8: Saree | G8: COD
A9: B-25687 | B9: 387 | C9: -213 | D9: 5 | E9: Clothing | F9: Saree | G9: UPI
A10: B-25643 | B10: 50 | C10: -44 | D10: 2 | E10: Clothing | F10: Hankerchief | G10: UPI
A11: B-25851 | B11: 135 | C11: -54 | D11: 5 | E11: Clothing | F11: Kurti | G11: COD
A12: B-25703 | B12: 231 | C12: -190 | D12: 9 | E12: Clothing | F12: Hankerchief | G12: COD
A13: B-25887 | B13: 2125 | C13: -234 | D13: 6 | E13: Electronics | F13: Printers | G13: EMI
... A1501: B-25993 | B1501: 4363 | C1501: 305 | D1501: 5 | E1501: Furniture | F1501: Tables | G1501: EMI
